{"wdi-EN.BIR.THRD.NO": {"data": {"2018": {"ATG": 3.0, "ABW": 2.0, "BHS": 10.0, "BHR": 7.0, "BRB": 4.0, "BLZ": 6.0, "BMU": 3.0, "VGB": 3.0, "CPV": 7.0, "CYM": 3.0, "COM": 14.0, "CUB": 19.0, "CUW": 2.0, "DMA": 7.0, "DOM": 17.0, "FJI": 14.0, "GRD": 2.0, "GNB": 12.0, "GUY": 16.0, "HTI": 17.0, "JAM": 11.0, "KIR": 6.0, "MDV": 0.0, "MHL": 4.0, "MUS": 12.0, "FSM": 12.0, "NRU": 2.0, "PLW": 6.0, "PNG": 39.0, "WSM": 6.0, "STP": 12.0, "SYC": 13.0, "SGP": 22.0, "SXM": 1.0, "SLB": 24.0, "KNA": 3.0, "LCA": 7.0, "VCT": 4.0, "SUR": 9.0, "TLS": 6.0, "TON": 5.0, "TTO": 5.0, "TCA": 4.0, "TUV": 1.0, "VUT": 8.0}, "recentValue": {"ATG": 3.0, "ABW": 2.0, "BHS": 10.0, "BMU": 3.0, "BHR": 7.0, "BRB": 4.0, "BLZ": 6.0, "VGB": 3.0, "CPV": 7.0, "CYM": 3.0, "COM": 14.0, "CUB": 19.0, "CUW": 2.0, "DMA": 7.0, "DOM": 17.0, "FJI": 14.0, "GRD": 2.0, "GNB": 12.0, "GUY": 16.0, "HTI": 17.0, "JAM": 11.0, "KIR": 6.0, "MDV": 0.0, "MHL": 4.0, "MUS": 12.0, "FSM": 12.0, "NRU": 2.0, "PLW": 6.0, "PNG": 39.0, "WSM": 6.0, "STP": 12.0, "SYC": 13.0, "SGP": 22.0, "SXM": 1.0, "SLB": 24.0, "KNA": 3.0, "VCT": 4.0, "LCA": 7.0, "SUR": 9.0, "TLS": 6.0, "TTO": 5.0, "TON": 5.0, "TUV": 1.0, "TCA": 4.0, "VUT": 8.0}, "recentYear": {"ATG": "2018", "ABW": "2018", "BHS": "2018", "BMU": "2018", "BHR": "2018", "BRB": "2018", "BLZ": "2018", "VGB": "2018", "CPV": "2018", "CYM": "2018", "COM": "2018", "CUB": "2018", "CUW": "2018", "DMA": "2018", "DOM": "2018", "FJI": "2018", "GRD": "2018", "GNB": "2018", "GUY": "2018", "HTI": "2018", "JAM": "2018", "KIR": "2018", "MDV": "2018", "MHL": "2018", "MUS": "2018", "FSM": "2018", "NRU": "2018", "PLW": "2018", "PNG": "2018", "WSM": "2018", "STP": "2018", "SYC": "2018", "SGP": "2018", "SXM": "2018", "SLB": "2018", "KNA": "2018", "VCT": "2018", "LCA": "2018", "SUR": "2018", "TLS": "2018", "TTO": "2018", "TON": "2018", "TUV": "2018", "TCA": "2018", "VUT": "2018"}}, "def": "Birds are listed for countries included within their breeding or wintering ranges. Threatened species are the number of species classified by the IUCN as endangered, vulnerable, rare, indeterminate, out of danger, or insufficiently known.", "name": "Bird species, threatened", "source": "United Nations Environmental Program and the World Conservation Monitoring Centre, and International Union for Conservation of Nature, Red List of Threatened Species.", "dataset": "United Nations Environmental Program and the World Conservation Monitoring Centre, and International Union for Conservation of Nature, Red List of Threatened Species.", "category": "Environment", "subcategory": "Biodiversity & protected areas", "link": "https://data.worldbank.org/indicator/wdi-EN.BIR.THRD.NO", "dim": "none", "priority": "1.0", "units": "threatened"}, "confidenceIntervals": {"2018": {"ATG": 0.42857142857142855, "BMU": 3.0, "CYM": 0.3, "DOM": 1.7, "GUY": 2.2857142857142856, "KIR": 0.8571428571428571, "MDV": 0.0, "MHL": 4.0, "FSM": 12.0, "NRU": 2.0, "PNG": 9.75, "WSM": 6.0, "SYC": 13.0, "LCA": 7.0, "TLS": 6.0, "TON": 0.5, "TCA": 4.0}, "recentValue": {"ABW": 0.2857142857142857, "BLZ": 6.0, "VGB": 0.3, "FJI": 2.0, "GRD": 2.0, "HTI": 1.7, "NRU": 2.0, "SYC": 1.3, "VCT": 1.0, "TON": 1.25, "TUV": 1.0}}, "featureImportances": {"indicators": {"wdi-DC.ODA.TOTL.KD": 0.902, "epi-ECO": 0.229, "wdi2-SP.POP.0004.MA.5Y": 0.138, "wdi2-TM.QTY.MRCH.XD.WD": 0.59, "wdi2-TX.VAL.MRCH.R6.ZS": 0.531, "wdi-LP.LPI.LOGS.XQ": 0.698, "wdi2-NE.CON.PRVT.PP.KD": 0.655, "ihme-cataract": 0.524, "wdi-AG.LND.ARBL.ZS": 0.836, "ndgain-nd-readiness-economic": 0.07}, "categories": {"Incentives": 0.307, "Mobility and communication": 0.01, "Child Mortality": 0.582, "Global Cybersecurity Index": 0.757}}}