{"wdi-IC.TAX.LABR.CP.ZS": {"data": {"2014": {"ATG": 10.3, "BHS": 6.3, "BHR": 13.5, "BRB": 12.2, "BLZ": 5.0, "CPV": 17.6, "COM": 0.0, "DMA": 7.9, "DOM": 18.6, "FJI": 10.4, "GRD": 5.6, "GNB": 24.8, "GUY": 9.2, "HTI": 12.4, "JAM": 13.3, "KIR": 8.5, "MDV": 7.9, "MHL": 11.8, "MUS": 6.8, "FSM": 8.5, "PLW": 9.5, "PNG": 11.7, "WSM": 6.8, "STP": 6.8, "SYC": 1.7, "SGP": 15.3, "SLB": 8.5, "KNA": 11.2, "LCA": 5.6, "VCT": 5.1, "SUR": 0.0, "TLS": 0.0, "TON": 5.6, "TTO": 8.2, "VUT": 4.5}, "2005": {"ATG": 9.5, "BLZ": 7.0, "CPV": 18.5, "COM": 0.0, "DMA": 7.9, "DOM": 8.5, "FJI": 10.2, "GRD": 5.6, "GNB": 24.8, "GUY": 8.8, "HTI": 12.4, "JAM": 13.0, "KIR": 8.5, "MDV": 0.0, "MHL": 11.8, "MUS": 6.6, "FSM": 6.8, "PLW": 6.5, "PNG": 10.9, "WSM": 6.8, "STP": 6.8, "SYC": 25.4, "SGP": 14.4, "SLB": 8.5, "KNA": 11.3, "LCA": 5.6, "VCT": 3.9, "SUR": 0.0, "TLS": 0.0, "TON": 0.0, "TTO": 8.3, "VUT": 4.5}, "2006": {"ATG": 9.5, "BLZ": 7.0, "CPV": 18.5, "COM": 0.0, "DMA": 7.9, "DOM": 8.9, "FJI": 10.2, "GRD": 5.6, "GNB": 24.8, "GUY": 8.8, "HTI": 12.4, "JAM": 13.0, "KIR": 8.5, "MDV": 0.0, "MHL": 11.8, "MUS": 6.6, "FSM": 6.8, "PLW": 6.5, "PNG": 10.9, "WSM": 6.8, "STP": 6.8, "SYC": 25.4, "SGP": 14.4, "SLB": 8.5, "KNA": 11.3, "LCA": 5.6, "VCT": 3.9, "SUR": 0.0, "TLS": 0.0, "TON": 0.0, "TTO": 8.3, "VUT": 4.5}, "2007": {"ATG": 9.5, "BHS": 4.5, "BHR": 14.7, "BLZ": 7.0, "CPV": 18.5, "COM": 0.0, "DMA": 7.9, "DOM": 9.5, "FJI": 10.2, "GRD": 5.6, "GNB": 24.8, "GUY": 8.8, "HTI": 12.4, "JAM": 13.0, "KIR": 8.5, "MDV": 0.0, "MHL": 11.8, "MUS": 6.6, "FSM": 6.8, "PLW": 6.5, "PNG": 10.9, "WSM": 6.8, "STP": 6.8, "SYC": 25.4, "SGP": 13.7, "SLB": 8.5, "KNA": 11.3, "LCA": 5.6, "VCT": 3.9, "SUR": 0.0, "TLS": 0.0, "TON": 0.0, "TTO": 8.3, "VUT": 4.5}, "2008": {"ATG": 9.5, "BHS": 4.5, "BHR": 14.7, "BLZ": 7.0, "CPV": 18.5, "COM": 0.0, "DMA": 7.9, "DOM": 13.4, "FJI": 10.2, "GRD": 5.6, "GNB": 24.8, "GUY": 8.8, "HTI": 12.4, "JAM": 13.0, "KIR": 8.5, "MDV": 0.0, "MHL": 11.8, "MUS": 7.8, "FSM": 6.8, "PLW": 6.5, "PNG": 10.9, "WSM": 6.8, "STP": 6.8, "SYC": 22.6, "SGP": 14.5, "SLB": 8.5, "KNA": 11.3, "LCA": 5.6, "VCT": 3.9, "SUR": 0.0, "TLS": 0.0, "TON": 0.0, "TTO": 8.3, "VUT": 4.5}, "2009": {"ATG": 9.5, "BHS": 4.5, "BHR": 14.7, "BLZ": 7.0, "CPV": 18.5, "COM": 0.0, "DMA": 7.9, "DOM": 17.8, "FJI": 10.2, "GRD": 5.6, "GNB": 24.8, "GUY": 8.8, "HTI": 12.4, "JAM": 13.0, "KIR": 8.5, "MDV": 0.0, "MHL": 11.8, "MUS": 8.1, "FSM": 6.8, "PLW": 6.5, "PNG": 11.7, "WSM": 6.8, "STP": 6.8, "SYC": 22.6, "SGP": 14.6, "SLB": 8.5, "KNA": 11.3, "LCA": 5.6, "VCT": 5.1, "SUR": 0.0, "TLS": 0.0, "TON": 0.0, "TTO": 8.3, "VUT": 4.5}, "2010": {"ATG": 9.5, "BHS": 4.5, "BHR": 13.5, "BLZ": 7.0, "CPV": 18.5, "COM": 0.0, "DMA": 7.9, "DOM": 18.3, "FJI": 10.2, "GRD": 5.6, "GNB": 24.8, "GUY": 8.8, "HTI": 12.4, "JAM": 13.0, "KIR": 8.5, "MDV": 0.0, "MHL": 11.8, "MUS": 8.6, "FSM": 6.8, "PLW": 6.5, "PNG": 11.7, "WSM": 6.8, "STP": 6.8, "SYC": 22.6, "SGP": 14.7, "SLB": 8.5, "KNA": 11.3, "LCA": 5.6, "VCT": 5.1, "SUR": 0.0, "TLS": 0.0, "TON": 0.0, "TTO": 8.3, "VUT": 4.5}, "2011": {"ATG": 9.5, "BHS": 6.1, "BHR": 13.5, "BRB": 12.7, "BLZ": 7.0, "CPV": 18.5, "COM": 0.0, "DMA": 7.9, "DOM": 18.6, "FJI": 10.2, "GRD": 5.6, "GNB": 24.8, "GUY": 8.8, "HTI": 12.4, "JAM": 13.0, "KIR": 8.5, "MDV": 0.0, "MHL": 11.8, "MUS": 10.2, "FSM": 7.0, "PLW": 6.5, "PNG": 11.7, "WSM": 6.8, "STP": 6.8, "SYC": 11.5, "SGP": 15.7, "SLB": 8.5, "KNA": 11.3, "LCA": 5.6, "VCT": 5.1, "SUR": 0.0, "TLS": 0.0, "TON": 0.0, "TTO": 8.3, "VUT": 4.5}, "2012": {"ATG": 9.5, "BHS": 6.1, "BHR": 13.5, "BRB": 12.3, "BLZ": 7.0, "CPV": 18.5, "COM": 0.0, "DMA": 7.9, "DOM": 18.6, "FJI": 10.2, "GRD": 5.6, "GNB": 24.8, "GUY": 8.8, "HTI": 12.4, "JAM": 12.9, "KIR": 8.5, "MDV": 5.3, "MHL": 11.8, "MUS": 10.2, "FSM": 7.9, "PLW": 9.3, "PNG": 11.7, "WSM": 6.8, "STP": 6.8, "SYC": 1.7, "SGP": 16.8, "SLB": 8.5, "KNA": 11.3, "LCA": 5.6, "VCT": 5.1, "SUR": 0.0, "TLS": 0.0, "TON": 0.0, "TTO": 8.3, "VUT": 4.5}, "2013": {"ATG": 9.4, "BHS": 6.3, "BHR": 13.5, "BRB": 12.2, "BLZ": 5.0, "CPV": 17.6, "COM": 0.0, "DMA": 7.9, "DOM": 18.6, "FJI": 10.4, "GRD": 5.6, "GNB": 24.8, "GUY": 8.8, "HTI": 12.4, "JAM": 12.9, "KIR": 8.5, "MDV": 7.9, "MHL": 11.8, "MUS": 6.8, "FSM": 7.9, "PLW": 9.2, "PNG": 11.7, "WSM": 6.8, "STP": 6.8, "SYC": 1.7, "SGP": 16.8, "SLB": 8.5, "KNA": 11.3, "LCA": 5.6, "VCT": 5.1, "SUR": 0.0, "TLS": 0.0, "TON": 5.6, "TTO": 7.6, "VUT": 4.5}, "2015": {"ATG": 10.7, "BHS": 6.3, "BHR": 13.5, "BRB": 12.2, "BLZ": 5.0, "CPV": 17.6, "COM": 0.0, "DMA": 7.9, "DOM": 18.6, "FJI": 10.4, "GRD": 5.6, "GNB": 24.8, "GUY": 9.2, "HTI": 12.4, "JAM": 13.4, "KIR": 8.5, "MDV": 7.9, "MHL": 11.8, "MUS": 7.4, "FSM": 8.5, "PLW": 9.5, "PNG": 11.7, "WSM": 6.8, "STP": 6.8, "SYC": 2.3, "SGP": 15.3, "SLB": 8.5, "KNA": 11.2, "LCA": 5.6, "VCT": 6.2, "SUR": 0.0, "TLS": 0.0, "TON": 5.6, "TTO": 8.5, "VUT": 4.5}, "2016": {"ATG": 10.7, "BHS": 6.3, "BHR": 13.5, "BRB": 12.2, "BLZ": 5.0, "CPV": 17.6, "COM": 0.0, "DMA": 7.9, "DOM": 18.6, "FJI": 12.7, "GRD": 5.6, "GNB": 24.8, "GUY": 9.2, "HTI": 12.4, "JAM": 13.4, "KIR": 8.5, "MDV": 7.9, "MHL": 11.8, "MUS": 7.7, "FSM": 8.5, "PLW": 9.5, "PNG": 11.7, "WSM": 7.3, "STP": 6.8, "SYC": 2.3, "SGP": 16.2, "SLB": 8.5, "KNA": 11.2, "LCA": 5.6, "VCT": 6.2, "SUR": 0.0, "TLS": 0.0, "TON": 5.6, "TTO": 8.5, "VUT": 4.5}, "2017": {"ATG": 10.7, "BHS": 6.3, "BHR": 13.5, "BRB": 12.2, "BLZ": 5.0, "CPV": 17.6, "COM": 0.0, "DMA": 7.9, "DOM": 18.6, "FJI": 12.7, "GRD": 5.6, "GNB": 24.8, "GUY": 9.2, "HTI": 12.4, "JAM": 13.4, "KIR": 8.5, "MDV": 7.9, "MHL": 11.8, "MUS": 7.9, "FSM": 8.5, "PLW": 9.6, "PNG": 11.7, "WSM": 8.5, "STP": 6.8, "SYC": 2.3, "SGP": 17.8, "SLB": 8.5, "KNA": 11.2, "LCA": 5.6, "VCT": 6.2, "SUR": 0.0, "TLS": 0.0, "TON": 5.6, "TTO": 9.4, "VUT": 4.5}, "2018": {"ATG": 11.8, "BHS": 6.3, "BHR": 13.5, "BRB": 12.3, "BLZ": 5.0, "CPV": 18.1, "COM": 0.0, "DMA": 7.9, "DOM": 18.6, "FJI": 12.6, "GRD": 5.6, "GNB": 24.8, "GUY": 9.2, "HTI": 12.4, "JAM": 13.4, "KIR": 8.5, "MDV": 7.9, "MHL": 12.8, "MUS": 8.1, "FSM": 8.5, "PLW": 9.9, "PNG": 11.7, "WSM": 8.5, "STP": 6.8, "SYC": 2.3, "SGP": 17.8, "SLB": 8.5, "KNA": 11.2, "LCA": 5.6, "VCT": 6.2, "SUR": 0.0, "TLS": 0.0, "TON": 5.6, "TTO": 9.4, "VUT": 4.5}, "2019": {"ATG": 12.1, "BHS": 6.4, "BHR": 13.5, "BRB": 12.7, "BLZ": 5.0, "CPV": 18.7, "COM": 0.0, "DMA": 7.9, "DOM": 18.6, "FJI": 12.4, "GRD": 5.6, "GNB": 24.8, "GUY": 9.2, "HTI": 12.4, "JAM": 13.4, "KIR": 8.5, "MDV": 7.9, "MHL": 13.0, "MUS": 8.2, "FSM": 8.5, "PLW": 10.7, "PNG": 9.5, "WSM": 8.5, "STP": 6.8, "SYC": 2.3, "SGP": 17.8, "SLB": 8.5, "KNA": 11.2, "LCA": 5.6, "VCT": 6.2, "SUR": 0.0, "TLS": 6.8, "TON": 5.6, "TTO": 9.4, "VUT": 4.5}, "recentValue": {"ATG": 12.1, "BHS": 6.4, "BHR": 13.5, "BRB": 12.7, "BLZ": 5.0, "CPV": 18.7, "COM": 0.0, "DMA": 7.9, "DOM": 18.6, "FJI": 12.4, "GRD": 5.6, "GNB": 24.8, "GUY": 9.2, "HTI": 12.4, "JAM": 13.4, "KIR": 8.5, "MDV": 7.9, "MHL": 13.0, "MUS": 8.2, "FSM": 8.5, "PLW": 10.7, "PNG": 9.5, "WSM": 8.5, "STP": 6.8, "SYC": 2.3, "SGP": 17.8, "SLB": 8.5, "KNA": 11.2, "VCT": 6.2, "LCA": 5.6, "SUR": 0.0, "TLS": 6.8, "TTO": 9.4, "TON": 5.6, "VUT": 4.5}, "recentYear": {"ATG": "2019", "BHS": "2019", "BHR": "2019", "BRB": "2019", "BLZ": "2019", "CPV": "2019", "COM": "2019", "DMA": "2019", "DOM": "2019", "FJI": "2019", "GRD": "2019", "GNB": "2019", "GUY": "2019", "HTI": "2019", "JAM": "2019", "KIR": "2019", "MDV": "2019", "MHL": "2019", "MUS": "2019", "FSM": "2019", "PLW": "2019", "PNG": "2019", "WSM": "2019", "STP": "2019", "SYC": "2019", "SGP": "2019", "SLB": "2019", "KNA": "2019", "VCT": "2019", "LCA": "2019", "SUR": "2019", "TLS": "2019", "TTO": "2019", "TON": "2019", "VUT": "2019"}}, "def": "Labor tax and contributions is the amount of taxes and mandatory contributions on labor paid by the business.", "name": "Labor tax and contributions", "source": "World Bank, Doing Business project (http://www.doingbusiness.org/).", "dataset": "World Bank, Doing Business project (http://www.doingbusiness.org/).", "category": "Private Sector & Trade", "subcategory": "Business environment", "link": "https://data.worldbank.org/indicator/wdi-IC.TAX.LABR.CP.ZS", "dim": "none", "priority": "1.0", "units": "% of commercial profits"}, "confidenceIntervals": {"2014": {"COM": 0.0, "FJI": 10.4, "KIR": 8.5, "PNG": 11.7, "STP": 0.6799999999999999, "SGP": 2.185714285714286, "SLB": 0.85, "TLS": 0.0}, "2005": {"ATG": 9.5, "GUY": 1.2571428571428573, "KIR": 8.5, "MUS": 0.6599999999999999, "WSM": 6.8, "STP": 1.7}, "2006": {"DOM": 0.89, "GNB": 24.8, "PLW": 1.625}, "2007": {"ATG": 1.3571428571428572, "BHR": 1.47, "BLZ": 0.7, "GRD": 0.7999999999999999, "FSM": 6.8, "SYC": 3.6285714285714286, "SGP": 3.425, "SLB": 1.2142857142857142, "TON": 0.0, "VUT": 0.45}, "2008": {"FSM": 0.9714285714285714, "STP": 1.7, "SYC": 22.6}, "2009": {"COM": 0.0, "DMA": 7.9, "GRD": 0.5599999999999999, "JAM": 3.25, "LCA": 1.4, "TLS": 0.0, "TON": 0.0, "TTO": 0.8300000000000001}, "2010": {"ATG": 2.375, "BLZ": 7.0, "FJI": 10.2, "GNB": 3.542857142857143, "FSM": 0.6799999999999999, "LCA": 5.6, "TLS": 0.0}, "2011": {"BLZ": 1.0, "GRD": 0.7999999999999999, "MUS": 1.02, "FSM": 7.0, "VCT": 0.51, "TTO": 8.3}, "2012": {"CPV": 2.642857142857143, "DOM": 2.6571428571428575, "JAM": 12.9, "MHL": 1.1800000000000002, "PLW": 0.93, "WSM": 0.6799999999999999, "STP": 1.7, "VCT": 0.51, "TON": 0.0, "TTO": 1.1857142857142857}, "2013": {"BHR": 1.9285714285714286, "CPV": 2.5142857142857147, "DOM": 4.65, "WSM": 0.9714285714285714, "STP": 0.6799999999999999, "LCA": 0.5599999999999999, "TON": 0.7999999999999999}, "2015": {"ATG": 1.5285714285714285, "COM": 0.0, "MUS": 1.0571428571428572, "FSM": 8.5, "PNG": 2.925, "SLB": 8.5, "LCA": 5.6, "TTO": 8.5}, "2016": {"FJI": 3.175, "JAM": 3.35, "KIR": 2.125, "PNG": 2.925, "WSM": 7.3, "SUR": 0.0, "TTO": 8.5}, "2017": {"ATG": 1.5285714285714285, "BHS": 6.3, "BRB": 1.7428571428571427, "DMA": 7.9, "DOM": 18.6, "FJI": 12.7, "MUS": 1.1285714285714286, "WSM": 0.85, "STP": 6.8, "VUT": 0.6428571428571429}, "2018": {"ATG": 11.8, "COM": 0.0, "GRD": 5.6, "GNB": 6.2, "MUS": 0.8099999999999999, "FSM": 0.85, "SLB": 2.125, "TLS": 0.0, "TON": 5.6, "TTO": 2.35}, "2019": {"BHR": 3.375, "COM": 0.0, "FJI": 3.1, "GRD": 0.7999999999999999, "KIR": 0.85, "MUS": 8.2, "STP": 6.8, "TTO": 1.342857142857143}, "recentValue": {"BRB": 1.8142857142857143, "DOM": 1.86, "FJI": 3.1, "GNB": 6.2, "KIR": 8.5, "MDV": 1.975, "FSM": 8.5, "WSM": 8.5, "SYC": 0.575, "SGP": 2.542857142857143, "VCT": 0.62, "TTO": 1.342857142857143}}, "featureImportances": {"indicators": {"ohi-liv-score": 0.462, "egov-osi": 0.588, "wdi2-NY.GNP.MKTP.CN.AD": 0.312, "ihme-cystic-echinococcosis": 0.187, "key-2": 0.68, "ndgain-id_food_01-raw": 0.954, "unicef-hivaidse5": 0.535, "wdi2-SH.XPD.GHED.PC.CD": 0.296, "wdi2-TM.TAX.MANF.BC.ZS": 0.077, "igrac-twap_ind_sids_humandepgwagricult": 0.767}, "categories": {"Sensitivity; Results": 0.016, "Management": 0.96, "Road injuries": 0.848, "None": 0.751}}}