{"wdi-IC.LGL.CRED.XQ": {"data": {"2014": {"ATG": 5.0, "BHS": 6.0, "BHR": 1.0, "BRB": 6.0, "BLZ": 4.0, "CPV": 1.0, "COM": 6.0, "DMA": 6.0, "DOM": 1.0, "FJI": 5.0, "GRD": 6.0, "GNB": 6.0, "GUY": 3.0, "HTI": 2.0, "JAM": 10.0, "KIR": 4.0, "MDV": 2.0, "MHL": 10.0, "MUS": 6.0, "FSM": 10.0, "PLW": 10.0, "PNG": 3.0, "WSM": 5.0, "STP": 0.0, "SYC": 2.0, "SGP": 8.0, "SLB": 10.0, "KNA": 5.0, "LCA": 5.0, "VCT": 5.0, "SUR": 2.0, "TLS": 0.0, "TON": 10.0, "TTO": 7.0, "VUT": 10.0}, "2013": {"ATG": 5.0, "BHS": 6.0, "BHR": 1.0, "BRB": 6.0, "BLZ": 4.0, "CPV": 1.0, "COM": 6.0, "DMA": 6.0, "DOM": 1.0, "FJI": 5.0, "GRD": 6.0, "GNB": 6.0, "GUY": 3.0, "HTI": 2.0, "JAM": 6.0, "KIR": 4.0, "MDV": 2.0, "MHL": 10.0, "MUS": 6.0, "FSM": 10.0, "PLW": 10.0, "PNG": 3.0, "WSM": 5.0, "STP": 0.0, "SYC": 2.0, "SGP": 8.0, "SLB": 10.0, "KNA": 5.0, "LCA": 5.0, "VCT": 5.0, "SUR": 2.0, "TLS": 0.0, "TON": 10.0, "TTO": 6.0, "VUT": 10.0}, "2015": {"ATG": 5.0, "BHS": 6.0, "BHR": 1.0, "BRB": 6.0, "BLZ": 4.0, "CPV": 1.0, "COM": 6.0, "DMA": 6.0, "DOM": 1.0, "FJI": 5.0, "GRD": 6.0, "GNB": 6.0, "GUY": 3.0, "HTI": 2.0, "JAM": 9.0, "KIR": 4.0, "MDV": 2.0, "MHL": 10.0, "MUS": 6.0, "FSM": 10.0, "PLW": 10.0, "PNG": 3.0, "WSM": 5.0, "STP": 0.0, "SYC": 2.0, "SGP": 8.0, "SLB": 10.0, "KNA": 5.0, "LCA": 5.0, "VCT": 5.0, "SUR": 2.0, "TLS": 0.0, "TON": 10.0, "TTO": 7.0, "VUT": 10.0}, "2016": {"ATG": 5.0, "BHS": 6.0, "BHR": 1.0, "BRB": 6.0, "BLZ": 4.0, "CPV": 1.0, "COM": 6.0, "DMA": 6.0, "DOM": 1.0, "FJI": 5.0, "GRD": 6.0, "GNB": 6.0, "GUY": 3.0, "HTI": 2.0, "JAM": 9.0, "KIR": 4.0, "MDV": 2.0, "MHL": 10.0, "MUS": 6.0, "FSM": 10.0, "PLW": 10.0, "PNG": 9.0, "WSM": 5.0, "STP": 0.0, "SYC": 2.0, "SGP": 8.0, "SLB": 10.0, "KNA": 5.0, "LCA": 5.0, "VCT": 5.0, "SUR": 2.0, "TLS": 0.0, "TON": 10.0, "TTO": 7.0, "VUT": 11.0}, "2017": {"ATG": 5.0, "BHS": 6.0, "BHR": 1.0, "BRB": 6.0, "BLZ": 4.0, "CPV": 1.0, "COM": 6.0, "DMA": 6.0, "DOM": 1.0, "FJI": 5.0, "GRD": 6.0, "GNB": 6.0, "GUY": 3.0, "HTI": 2.0, "JAM": 9.0, "KIR": 4.0, "MDV": 2.0, "MHL": 10.0, "MUS": 6.0, "FSM": 10.0, "PLW": 10.0, "PNG": 9.0, "WSM": 9.0, "STP": 0.0, "SYC": 2.0, "SGP": 8.0, "SLB": 10.0, "KNA": 5.0, "LCA": 5.0, "VCT": 5.0, "SUR": 2.0, "TLS": 0.0, "TON": 10.0, "TTO": 7.0, "VUT": 11.0}, "2018": {"ATG": 5.0, "BHS": 6.0, "BHR": 1.0, "BRB": 6.0, "BLZ": 4.0, "CPV": 1.0, "COM": 6.0, "DMA": 6.0, "DOM": 1.0, "FJI": 5.0, "GRD": 6.0, "GNB": 6.0, "GUY": 3.0, "HTI": 2.0, "JAM": 9.0, "KIR": 4.0, "MDV": 2.0, "MHL": 10.0, "MUS": 6.0, "FSM": 10.0, "PLW": 10.0, "PNG": 9.0, "WSM": 9.0, "STP": 0.0, "SYC": 2.0, "SGP": 8.0, "SLB": 10.0, "KNA": 5.0, "LCA": 5.0, "VCT": 5.0, "SUR": 2.0, "TLS": 0.0, "TON": 10.0, "TTO": 7.0, "VUT": 11.0}, "2019": {"ATG": 5.0, "BHS": 6.0, "BHR": 3.0, "BRB": 6.0, "BLZ": 4.0, "CPV": 1.0, "COM": 6.0, "DMA": 6.0, "DOM": 1.0, "FJI": 5.0, "GRD": 6.0, "GNB": 6.0, "GUY": 3.0, "HTI": 2.0, "JAM": 9.0, "KIR": 4.0, "MDV": 2.0, "MHL": 10.0, "MUS": 6.0, "FSM": 10.0, "PLW": 10.0, "PNG": 9.0, "WSM": 9.0, "STP": 0.0, "SYC": 2.0, "SGP": 8.0, "SLB": 10.0, "KNA": 5.0, "LCA": 5.0, "VCT": 5.0, "SUR": 2.0, "TLS": 0.0, "TON": 10.0, "TTO": 7.0, "VUT": 11.0}, "recentValue": {"ATG": 5.0, "BHS": 6.0, "BHR": 3.0, "BRB": 6.0, "BLZ": 4.0, "CPV": 1.0, "COM": 6.0, "DMA": 6.0, "DOM": 1.0, "FJI": 5.0, "GRD": 6.0, "GNB": 6.0, "GUY": 3.0, "HTI": 2.0, "JAM": 9.0, "KIR": 4.0, "MDV": 2.0, "MHL": 10.0, "MUS": 6.0, "FSM": 10.0, "PLW": 10.0, "PNG": 9.0, "WSM": 9.0, "STP": 0.0, "SYC": 2.0, "SGP": 8.0, "SLB": 10.0, "KNA": 5.0, "VCT": 5.0, "LCA": 5.0, "SUR": 2.0, "TLS": 0.0, "TTO": 7.0, "TON": 10.0, "VUT": 11.0}, "recentYear": {"ATG": "2019", "BHS": "2019", "BHR": "2019", "BRB": "2019", "BLZ": "2019", "CPV": "2019", "COM": "2019", "DMA": "2019", "DOM": "2019", "FJI": "2019", "GRD": "2019", "GNB": "2019", "GUY": "2019", "HTI": "2019", "JAM": "2019", "KIR": "2019", "MDV": "2019", "MHL": "2019", "MUS": "2019", "FSM": "2019", "PLW": "2019", "PNG": "2019", "WSM": "2019", "STP": "2019", "SYC": "2019", "SGP": "2019", "SLB": "2019", "KNA": "2019", "VCT": "2019", "LCA": "2019", "SUR": "2019", "TLS": "2019", "TTO": "2019", "TON": "2019", "VUT": "2019"}}, "def": "Strength of legal rights index measures the degree to which collateral and bankruptcy laws protect the rights of borrowers and lenders and thus facilitate lending. The index ranges from 0 to 12, with higher scores indicating that these laws are better designed to expand access to credit.", "name": "Strength of legal rights index", "source": "World Bank, Doing Business project (http://www.doingbusiness.org/).", "dataset": "World Bank, Doing Business project (http://www.doingbusiness.org/).", "category": "Private Sector & Trade", "subcategory": "Business environment", "link": "https://data.worldbank.org/indicator/wdi-IC.LGL.CRED.XQ", "dim": "none", "priority": "1.0", "units": "0=weak to 12=strong"}, "confidenceIntervals": {"2014": {"ATG": 0.5, "KIR": 1.0, "MHL": 2.5, "FSM": 1.0, "WSM": 1.25, "VCT": 1.25, "TON": 1.0, "TTO": 1.75}, "2013": {"ATG": 0.5, "BLZ": 4.0, "DMA": 1.5, "GUY": 0.75, "HTI": 0.2, "JAM": 0.8571428571428571, "MDV": 0.2, "FSM": 10.0, "PLW": 10.0, "VCT": 1.25}, "2015": {"BHS": 0.8571428571428571, "BHR": 0.14285714285714285, "BRB": 6.0, "JAM": 0.9, "KIR": 4.0, "PNG": 0.42857142857142855, "WSM": 0.7142857142857143, "KNA": 0.5, "TTO": 0.7, "VUT": 2.5}, "2016": {"DMA": 6.0, "GNB": 1.5, "GUY": 3.0, "MDV": 0.2, "SLB": 10.0, "KNA": 0.7142857142857143, "SUR": 2.0}, "2017": {"CPV": 1.0, "DMA": 0.8571428571428571, "HTI": 0.2857142857142857, "KIR": 1.0, "MDV": 0.2, "MHL": 2.5, "PNG": 1.2857142857142858, "STP": 0.0, "SLB": 2.5, "SUR": 0.2857142857142857}, "2018": {"BRB": 1.5, "BLZ": 4.0, "HTI": 0.2, "MUS": 0.6, "STP": 0.0, "KNA": 0.7142857142857143}, "2019": {"DMA": 0.8571428571428571, "GRD": 0.6, "GUY": 0.3, "JAM": 0.9, "MDV": 0.2, "VUT": 1.1}, "recentValue": {"ATG": 0.7142857142857143, "CPV": 1.0, "COM": 0.6, "DOM": 0.14285714285714285, "HTI": 0.5, "VCT": 5.0, "SUR": 2.0, "TLS": 0.0}}, "featureImportances": {"indicators": {"ohi-fp-score": 0.885, "wdi2-SE.SEC.TCAQ.FE.ZS": 0.715, "itu-fbs1": 0.926, "hdr-49006": 0.639, "wdi2-SL.TLF.0714.SW.TM": 0.046, "wdi2-NY.GDP.FCST.CN": 0.408, "wdi2-SP.DYN.LE00.IN": 0.876, "ihme-mesothelioma": 0.109, "irena-one-cap-on": 0.279, "ohi-cw-score": 0.797}, "categories": {"Social Protection & Labor": 0.624, "HIV/AIDS Intervention Coverage": 0.522, "Nutrition: Children, Women, and Households": 0.22, "Adolescents": 0.078}}}