{"unicef-ecd10": {"data": {"recentValue": {}, "recentYear": {}}, "def": "Percentage of children 36\u201359 months old with whom an adult has engaged in four or more of the following activities to promote learning and school readiness in the past three days: a) reading books to the child, b) telling stories to the child, c) singing songs to the child, d) taking the child outside the home, e) playing with the child, and f) spending time with the child naming, counting or drawing things.", "name": "Early stimulation and responsive care by adults", "source": "DHS, MICS and other national surveys. Last update: June 2021.", "dataset": "DHS, MICS and other national surveys. Last update: June 2021.", "category": "Early Childhood Develompent", "subcategory": "None", "link": "https://www.unicef.org/reports/state-worlds-children-2021", "dim": "Richest 20%", "priority": "1.0", "units": "%"}, "confidenceIntervals": {"recentValue": {}}, "featureImportances": {"indicators": {"unicef-cp15": 0.144, "wdi2-NY.GDP.PCAP.CN": 0.478, "ihme-nasopharynx-cancer": 0.473, "ihme-gastroesophageal-reflux-disease": 0.069, "unicef-spe2": 0.97, "wdi2-NE.DAB.TOTL.CN": 0.56, "wdi-IT.CEL.SETS.P2": 0.855, "wdi-EG.ELC.FOSL.ZS": 0.516, "wdi-AG.CON.FERT.PT.ZS": 0.032, "ohi-mar-status": 0.907}, "categories": {"Self-harm": 0.407, "Other non-communicable diseases": 0.038, "Mental disorders": 0.553, "Upper digestive system diseases": 0.399}}}