{"paris-159": {"data": {"2015": {"BLZ": 2.7, "CPV": 0.0, "CUB": 34.3, "DOM": 8.2, "FJI": 0.0, "GNB": 0.0, "GUY": 5.5, "HTI": 0.0, "JAM": 0.0, "MUS": 5.5, "PNG": 2.7, "WSM": 0.0, "SLB": 2.7, "TLS": 2.7, "VUT": 2.7}, "2016": {"BHS": 2.7, "BLZ": 0.0, "CPV": 0.0, "CUB": 7.1, "DOM": 25.2, "FJI": 0.0, "GNB": 0.0, "GUY": 0.0, "HTI": 0.0, "JAM": 0.0, "MUS": 4.4, "PNG": 2.7, "WSM": 0.0, "SLB": 0.0, "SUR": 0.0, "TLS": 0.0, "TTO": 0.0, "VUT": 2.7}, "2017": {"BHS": 0.0, "BLZ": 2.4, "CPV": 0.0, "CUB": 0.0, "DOM": 9.7, "FJI": 0.0, "GNB": 0.0, "GUY": 0.0, "HTI": 0.0, "JAM": 0.0, "MUS": 0.0, "PNG": 2.4, "WSM": 0.0, "SLB": 0.0, "SUR": 0.0, "TLS": 0.0, "TTO": 0.0, "VUT": 2.4}, "2018": {"BHS": 0.0, "BLZ": 3.6, "CPV": 0.0, "CUB": 0.0, "DOM": 14.4, "FJI": 0.0, "GNB": 0.0, "GUY": 0.0, "HTI": 0.0, "JAM": 0.0, "MUS": 0.0, "PNG": 3.6, "WSM": 0.0, "SLB": 0.0, "SUR": 0.0, "TLS": 0.0, "TTO": 0.0, "VUT": 10.1}, "recentValue": {"BHS": 0.0, "BLZ": 3.6, "CPV": 0.0, "CUB": 0.0, "DOM": 14.4, "FJI": 0.0, "GNB": 0.0, "GUY": 0.0, "HTI": 0.0, "JAM": 0.0, "MUS": 0.0, "PNG": 3.6, "WSM": 0.0, "SLB": 0.0, "SUR": 0.0, "TLS": 0.0, "TTO": 0.0, "VUT": 10.1}, "recentYear": {"BHS": "2018", "BLZ": "2018", "CPV": "2018", "CUB": "2018", "DOM": "2018", "FJI": "2018", "GNB": "2018", "GUY": "2018", "HTI": "2018", "JAM": "2018", "MUS": "2018", "PNG": "2018", "WSM": "2018", "SLB": "2018", "SUR": "2018", "TLS": "2018", "TTO": "2018", "VUT": "2018"}}, "def": "Coverage Element 5 for ODIN data coverage score. It measures whether data are available at the second administrative level.", "name": "", "source": "Open Data Watch - Open Data Inventory", "dataset": "Open Data Watch - Open Data Inventory", "category": "Skills & Knowledge", "subcategory": "None", "link": "https://odin.opendatawatch.com/Downloads/otherFiles/ODIN-2018-Methodology.pdf", "dim": "None", "priority": "1.0", "units": "index (0 to 100)"}, "confidenceIntervals": {"2015": {"CPV": 0.0, "DOM": 0.82, "HTI": 0.0, "MUS": 5.5, "WSM": 0.0}, "2016": {"GNB": 0.0, "MUS": 0.6285714285714287, "TLS": 0.0}, "2017": {"BHS": 0.0, "CPV": 0.0, "CUB": 0.0, "MUS": 0.0}, "2018": {"DOM": 14.4, "GUY": 0.0, "WSM": 0.0, "SLB": 0.0}, "recentValue": {"BLZ": 0.9, "CPV": 0.0, "JAM": 0.0, "WSM": 0.0, "SLB": 0.0, "TLS": 0.0, "TTO": 0.0, "VUT": 10.1}}, "featureImportances": {"indicators": {"hdr-174306": 0.601, "igrac-twap_sids_hydrogeological_gwdisch": 0.29, "unicef-ecd9": 0.662, "wdi2-SH.DYN.NCOM.ZS": 0.481, "wdi2-SP.POP.6569.MA.5Y": 0.11, "wdi2-NE.CON.TOTL.KN": 0.947, "unicef-ch11": 0.534, "irena-rmw-gen-on": 0.871, "unicef-e13": 0.062, "wdi2-SE.SEC.CMPT.LO.ZS": 0.781}, "categories": {"Characteristic": 0.612, "Ocean renewable energy R&D budgets": 0.833, "UN E-Government Survey": 0.764, "Bacterial skin diseases": 0.031}}}